geoip2-stubs/METADATA.toml
geoip2-stubs/__init__.pyi
geoip2-stubs/database.pyi
geoip2-stubs/errors.pyi
geoip2-stubs/mixins.pyi
geoip2-stubs/models.pyi
geoip2-stubs/records.pyi
types_geoip2-3.0.0.dist-info/METADATA
types_geoip2-3.0.0.dist-info/WHEEL
types_geoip2-3.0.0.dist-info/top_level.txt
types_geoip2-3.0.0.dist-info/RECORD
