Metadata-Version: 2.1
Name: types-geoip2
Version: 3.0.0
Summary: Typing stubs for geoip2
Home-page: https://github.com/python/typeshed
License: Apache-2.0 license
Platform: UNKNOWN
Classifier: License :: OSI Approved :: Apache Software License
Classifier: Typing :: Typed
